b64_stream/_b64_stream.pxd
b64_stream/_b64_stream.c
b64_stream/_b64_stream.pyx
b64_stream/__init__.py
b64_stream/_b64_stream.cpython-38-x86_64-linux-gnu.so
b64_stream-1.0.0.dist-info/top_level.txt
b64_stream-1.0.0.dist-info/RECORD
b64_stream-1.0.0.dist-info/METADATA
b64_stream-1.0.0.dist-info/LICENSE
b64_stream-1.0.0.dist-info/WHEEL
