Metadata-Version: 2.1
Name: b64-stream
Version: 1.0.0
Summary: Base64 stream encode/decode library
Home-page: https://github.com/ikrivosheev/py-base64
Author: Ivan Krivosheev
Author-email: py.krivosheev@gmail.com
License: Apache 2
Platform: UNKNOWN
Classifier: Development Status :: 5 - Production/Stable
Classifier: Intended Audience :: Developers
Classifier: Topic :: Software Development :: Build Tools
Classifier: License :: OSI Approved :: Apache Software License
Classifier: Programming Language :: Python :: 3
Classifier: Programming Language :: Python :: 3.6
Classifier: Programming Language :: Python :: 3.7
Classifier: Programming Language :: Python :: 3.8
Classifier: Programming Language :: Python :: Implementation :: CPython
Requires-Python: >=3.5
